README.md
setup.py
memory_layout/__init__.py
memory_layout/__main__.py
memory_layout/simpleyaml.py
memory_layout/structs.py
memory_layout.egg-info/PKG-INFO
memory_layout.egg-info/SOURCES.txt
memory_layout.egg-info/dependency_links.txt
memory_layout.egg-info/entry_points.txt
memory_layout.egg-info/top_level.txt
memory_layout/renderers/__init__.py
memory_layout/renderers/dot.py
memory_layout/renderers/svg.py