Metadata-Version: 2.1
Name: memory-layout
Version: 0.0.30
Summary: Generating diagrams to show memory map layouts from code or definition files
Home-page: https://github.com/gerph/memory-layout-diagram
Author: Charles Ferguson
Author-email: gerph@gerph.org
License: MIT
Keywords: diagram,generator,memory-map
Platform: UNKNOWN
Classifier: Development Status :: 4 - Beta
Classifier: Intended Audience :: Developers
Classifier: License :: OSI Approved :: MIT License
Classifier: Programming Language :: Python :: 2.7
Classifier: Programming Language :: Python :: 3
Classifier: Operating System :: OS Independent
Requires-Python: >=2.7
